jupyterlab_doc_reader_extension/__init__.py
jupyterlab_doc_reader_extension/_version.py
jupyterlab_doc_reader_extension/handlers.py
jupyterlab_doc_reader_extension/tests/__init__.py
jupyterlab_doc_reader_extension/tests/conftest.py
jupyterlab_doc_reader_extension/tests/test_handlers.py
jupyterlab_doc_reader_extension-1.1.8.data/data/etc/jupyter/jupyter_server_config.d/jupyterlab_doc_reader_extension.json
jupyterlab_doc_reader_extension-1.1.8.data/data/share/jupyter/labextensions/jupyterlab_doc_reader_extension/package.json
jupyterlab_doc_reader_extension-1.1.8.data/data/share/jupyter/labextensions/jupyterlab_doc_reader_extension/static/728.09ab50c860da660c9699.js
jupyterlab_doc_reader_extension-1.1.8.data/data/share/jupyter/labextensions/jupyterlab_doc_reader_extension/static/777.d3e3cee0847cf8c2b684.js
jupyterlab_doc_reader_extension-1.1.8.data/data/share/jupyter/labextensions/jupyterlab_doc_reader_extension/static/remoteEntry.5e9e9fe5cdf978f744d7.js
jupyterlab_doc_reader_extension-1.1.8.data/data/share/jupyter/labextensions/jupyterlab_doc_reader_extension/static/style.js
jupyterlab_doc_reader_extension-1.1.8.data/data/share/jupyter/labextensions/jupyterlab_doc_reader_extension/static/third-party-licenses.json
jupyterlab_doc_reader_extension-1.1.8.data/data/share/jupyter/labextensions/jupyterlab_doc_reader_extension/install.json
jupyterlab_doc_reader_extension-1.1.8.dist-info/METADATA
jupyterlab_doc_reader_extension-1.1.8.dist-info/WHEEL
jupyterlab_doc_reader_extension-1.1.8.dist-info/licenses/LICENSE
jupyterlab_doc_reader_extension-1.1.8.dist-info/RECORD
