Metadata-Version: 2.4
Name: jupyterlab_doc_reader_extension
Version: 1.1.8
Summary: JupyterLab extension that allows reading of DOCX, PPTX, and RTF documents
Project-URL: Homepage, https://github.com/stellarshenson/jupyterlab_doc_reader_extension.git
Project-URL: Bug Tracker, https://github.com/stellarshenson/jupyterlab_doc_reader_extension/issues
Project-URL: Repository, https://github.com/stellarshenson/jupyterlab_doc_reader_extension.git
Author-email: Stellars Henson <konrad.jelen@gmail.com>
License: BSD 3-Clause License
License-File: LICENSE
Keywords: jupyter,jupyterlab,jupyterlab-extension
Classifier: Framework :: Jupyter
Classifier: Framework :: Jupyter :: JupyterLab
Classifier: Framework :: Jupyter :: JupyterLab :: 4
Classifier: Framework :: Jupyter :: JupyterLab :: Extensions
Classifier: Framework :: Jupyter :: JupyterLab :: Extensions :: Prebuilt
Classifier: License :: OSI Approved :: BSD License
Classifier: Programming Language :: Python
Classifier: Programming Language :: Python :: 3
Classifier: Programming Language :: Python :: 3.9
Classifier: Programming Language :: Python :: 3.10
Classifier: Programming Language :: Python :: 3.11
Classifier: Programming Language :: Python :: 3.12
Classifier: Programming Language :: Python :: 3.13
Requires-Python: >=3.9
Requires-Dist: pillow>=9.0.0
Requires-Dist: python-docx>=1.0.0
Requires-Dist: python-pptx>=0.6.21
Requires-Dist: reportlab>=4.0.0
Provides-Extra: test
Requires-Dist: coverage; extra == 'test'
Requires-Dist: pytest; extra == 'test'
Requires-Dist: pytest-asyncio; extra == 'test'
Requires-Dist: pytest-cov; extra == 'test'
Requires-Dist: pytest-jupyter[server]>=0.6.0; extra == 'test'
